polysort/__init__.py
polysort-0.0.3.dist-info/METADATA
polysort-0.0.3.dist-info/WHEEL
polysort-0.0.3.dist-info/top_level.txt
polysort-0.0.3.dist-info/RECORD
