Metadata-Version: 2.1
Name: polysort
Version: 0.0.3
Summary: A collection of sorting algorithms
Home-page: https://github.com/chaseburton/polysort
Author: Chase Burton Taylor
Author-email: ctaylor@citycollege.sheffield.eu
License: MIT
Project-URL: Documentation, http://polysort.readthedocs.org
Project-URL: Source Code, https://github.com/chaseburton/polysort
Classifier: Development Status :: 3 - Alpha
Classifier: Intended Audience :: Science/Research
Classifier: Topic :: Scientific/Engineering :: Artificial Intelligence
Classifier: License :: OSI Approved :: MIT License
Classifier: Programming Language :: Python
Classifier: Programming Language :: Python :: 3
Classifier: Programming Language :: Python :: 3.7
Classifier: Programming Language :: Python :: 3.8
Classifier: Programming Language :: Python :: 3.9
